iterables.py
iterables_decorator-0.1.1.dist-info/METADATA
iterables_decorator-0.1.1.dist-info/WHEEL
iterables_decorator-0.1.1.dist-info/top_level.txt
iterables_decorator-0.1.1.dist-info/RECORD
