Metadata-Version: 2.1
Name: iterables-decorator
Version: 0.1.1
Summary: Decorator to convert a class into an iterable.
Home-page: https://github.com/mr-strawberry66/iterables-decorator
